{
  "db_name": "SQLite",
  "query": "SELECT * from recipes WHERE id = ?",
  "describe": {
    "columns": [
      {
        "name": "id",
        "ordinal": 0,
        "type_info": "Int64"
      },
      {
        "name": "author",
        "ordinal": 1,
        "type_info": "Text"
      },
      {
        "name": "name",
        "ordinal": 2,
        "type_info": "Text"
      },
      {
        "name": "description",
        "ordinal": 3,
        "type_info": "Text"
      },
      {
        "name": "difficulty",
        "ordinal": 4,
        "type_info": "Text"
      },
      {
        "name": "estimated_duration",
        "ordinal": 5,
        "type_info": "Text"
      }
    ],
    "parameters": {
      "Right": 1
    },
    "nullable": [
      false,
      true,
      false,
      true,
      true,
      true
    ]
  },
  "hash": "e5a7dc9e993b418c725bb00bcbf0577916ab6a655a9c61a091b1bd1cb1494ff7"
}
